ffbb_api_client/__init__.py
ffbb_api_client/agenda_and_results.py
ffbb_api_client/area.py
ffbb_api_client/basketball_court.py
ffbb_api_client/category.py
ffbb_api_client/championship.py
ffbb_api_client/club_details.py
ffbb_api_client/club_infos.py
ffbb_api_client/competition.py
ffbb_api_client/competition_type.py
ffbb_api_client/converters.py
ffbb_api_client/day.py
ffbb_api_client/default.py
ffbb_api_client/field.py
ffbb_api_client/geo_location.py
ffbb_api_client/geographycale_zone.py
ffbb_api_client/group.py
ffbb_api_client/history.py
ffbb_api_client/http_requests_utils.py
ffbb_api_client/item.py
ffbb_api_client/league.py
ffbb_api_client/match.py
ffbb_api_client/match_detail.py
ffbb_api_client/member.py
ffbb_api_client/municipality.py
ffbb_api_client/news.py
ffbb_api_client/page_info.py
ffbb_api_client/practice_offers.py
ffbb_api_client/resource_id.py
ffbb_api_client/score.py
ffbb_api_client/season.py
ffbb_api_client/sex.py
ffbb_api_client/snippet.py
ffbb_api_client/standing.py
ffbb_api_client/team.py
ffbb_api_client/thumbnails.py
ffbb_api_client/type_association.py
ffbb_api_client/videos.py
ffbb_api_client-1.0.0.0.dist-info/licenses/LICENSE.txt
ffbb_api_client-1.0.0.0.dist-info/METADATA
ffbb_api_client-1.0.0.0.dist-info/WHEEL
ffbb_api_client-1.0.0.0.dist-info/top_level.txt
ffbb_api_client-1.0.0.0.dist-info/RECORD
