Metadata-Version: 2.4
Name: ffbb_api_client
Version: 1.0.0.0
Summary: Allow to interact with FFBB apis
Home-page: https://github.com/Rinzler78/FFBBApiClient_Python
Author: Rinzler78
Author-email: Borisleclere@gmail.com
License: Apache-2.0
Project-URL: Documentation, https://pyscaffold.org/
Platform: any
Classifier: Development Status :: 4 - Beta
Classifier: Programming Language :: Python
License-File: LICENSE.txt
Requires-Dist: importlib-metadata; python_version < "3.8"
Requires-Dist: requests
Requires-Dist: python-dotenv
Requires-Dist: readme_renderer
Requires-Dist: python-dateutil
Requires-Dist: requests_cache
Provides-Extra: testing
Requires-Dist: setuptools; extra == "testing"
Requires-Dist: pytest; extra == "testing"
Requires-Dist: pytest-cov; extra == "testing"
Dynamic: license-file
